googlenews/__init__.py
googlenews/cli.py
googlenews/googlenews.py
pynews_google-0.1.2.dist-info/LICENSE
pynews_google-0.1.2.dist-info/METADATA
pynews_google-0.1.2.dist-info/WHEEL
pynews_google-0.1.2.dist-info/entry_points.txt
pynews_google-0.1.2.dist-info/top_level.txt
pynews_google-0.1.2.dist-info/RECORD
