Metadata-Version: 2.1
Name: pynews-google
Version: 0.1.2
Summary: A Python library to fetch and parse Google News feeds
Home-page: https://github.com/AmosMaru/googlenews
Author: Amos Maru
Author-email: amosmaru10@gmail.com
License: UNKNOWN
Platform: UNKNOWN
Classifier: Programming Language :: Python :: 3
Classifier: License :: OSI Approved :: MIT License
Classifier: Operating System :: OS Independent
Requires-Python: >=3.6
License-File: LICENSE
Requires-Dist: beautifulsoup4
Requires-Dist: dateparser
Requires-Dist: feedparser
Requires-Dist: requests
